pydongo/__init__.py
pydongo/drivers/__init__.py
pydongo/drivers/async_mongo.py
pydongo/drivers/base.py
pydongo/drivers/mock.py
pydongo/drivers/motor.py
pydongo/drivers/sync_mongo.py
pydongo/expressions/__init__.py
pydongo/expressions/base.py
pydongo/expressions/field.py
pydongo/expressions/filter.py
pydongo/expressions/index.py
pydongo/expressions/mutation.py
pydongo/py.typed
pydongo/utils/__init__.py
pydongo/utils/annotations.py
pydongo/utils/serializer.py
pydongo/workers/collection.py
pydongo/workers/document.py
pydongo-0.6.1.dist-info/WHEEL
pydongo-0.6.1.dist-info/METADATA
pydongo-0.6.1.dist-info/RECORD
