Metadata-Version: 2.4
Name: pydongo
Version: 0.6.1
Summary: A lightweight ORM for MongoDB using Pydantic models.
Keywords: mongodb,pydantic,orm,async,motor
Author: Samuel Abolo
Author-email: Samuel Abolo <ikabolo59@gmail.com>
License-Expression: MIT
Classifier: Development Status :: 4 - Beta
Classifier: Intended Audience :: Developers
Classifier: License :: OSI Approved :: MIT License
Classifier: Operating System :: OS Independent
Classifier: Programming Language :: Python :: 3
Classifier: Programming Language :: Python :: 3.10
Classifier: Programming Language :: Python :: 3.11
Classifier: Programming Language :: Python :: 3.12
Classifier: Programming Language :: Python :: 3.13
Classifier: Topic :: Database
Classifier: Topic :: Software Development :: Libraries
Classifier: Typing :: Typed
Requires-Dist: motor>=3.7.1
Requires-Dist: pydantic>=2.11.9
Requires-Dist: pymongo>=4.15.2
Requires-Dist: tomli-w>=1.2.0
Requires-Python: >=3.10
Project-URL: Documentation, https://tecnosam.github.io/pydongo/
Project-URL: GitHub, https://github.com/tecnosam/pydongo
Project-URL: Homepage, https://github.com/tecnosam/pydongo
